compare_mt/__init__.py
compare_mt/align_utils.py
compare_mt/arg_utils.py
compare_mt/bucketers.py
compare_mt/cache_utils.py
compare_mt/compare_ll_main.py
compare_mt/compare_mt_main.py
compare_mt/corpus_utils.py
compare_mt/formatting.py
compare_mt/ngram_utils.py
compare_mt/print_utils.py
compare_mt/reporters.py
compare_mt/scorers.py
compare_mt/sign_utils.py
compare_mt/stat_utils.py
compare_mt/version_info.py
compare_mt/rouge/__init__.py
compare_mt/rouge/io.py
compare_mt/rouge/rouge.py
compare_mt/rouge/rouge_scorer.py
compare_mt/rouge/scoring.py
compare_mt/rouge/tokenize.py
tests/__init__.py
tests/test_cache.py
tests/test_scorers.py
compare_mt-0.2.10.dist-info/LICENSE
compare_mt-0.2.10.dist-info/METADATA
compare_mt-0.2.10.dist-info/WHEEL
compare_mt-0.2.10.dist-info/entry_points.txt
compare_mt-0.2.10.dist-info/top_level.txt
compare_mt-0.2.10.dist-info/RECORD
