Metadata-Version: 2.1
Name: compare-mt
Version: 0.2.10
Summary: Holistic comparison of the output of text generation models
Home-page: https://github.com/neulab/compare-mt
Author: Graham Neubig
License: BSD 3-Clause
Platform: UNKNOWN
Classifier: Intended Audience :: Developers
Classifier: Topic :: Text Processing
Classifier: Topic :: Scientific/Engineering :: Artificial Intelligence
Classifier: License :: OSI Approved :: BSD License
Classifier: Programming Language :: Python :: 3
License-File: LICENSE
Requires-Dist: nltk (>=3.2)
Requires-Dist: numpy
Requires-Dist: matplotlib
Requires-Dist: absl-py
Requires-Dist: sacrebleu
